ecws/__init__.py
ecws/segment.py
ecws/my_library/__init__.py
ecws/my_library/dataset_reader/__init__.py
ecws/my_library/dataset_reader/crf_dataset_reader.py
ecws/my_library/dataset_reader/cws_bert_dataset_reader.py
ecws/my_library/dataset_reader/raw_rsv_cws_bert_dataset_reader.py
ecws/my_library/fields/SequenceArrayField.py
ecws/my_library/fields/__init__.py
ecws/my_library/model/__init__.py
ecws/my_library/model/cws_bert_model.py
ecws/my_library/model/cws_model.py
ecws/my_library/predictors/__init__.py
ecws/my_library/predictors/cws_predictors.py
ecws/my_library/token_indexers/__init__.py
ecws/my_library/token_indexers/text_id_token_indexer.py
ecws/my_library/tokenizers/__init__.py
ecws/my_library/tokenizers/raw_rsv_pretrained_transformer_tokenizer.py
ecws/my_library/tokenizers/utils/__init__.py
ecws/my_library/tokenizers/utils/raw_rsv_bert_tokenizer.py
ecws/my_library/tokenizers/utils/raw_rsv_bert_tokenizer_bak.py
ecws/my_library/tokenizers/utils/raw_rsv_simple_token.py
ecws/my_library/tokenizers/utils/raw_rsv_token.py
ecws/my_library/tokenizers/utils/token_1_0_0.py
tests/__init__.py
tests/test_load_and_segment.py
ecws-3.0.5.dist-info/LICENSE.txt
ecws-3.0.5.dist-info/METADATA
ecws-3.0.5.dist-info/WHEEL
ecws-3.0.5.dist-info/top_level.txt
ecws-3.0.5.dist-info/RECORD
