Metadata-Version: 2.1
Name: ecws
Version: 3.0.5
Summary: 面向电力领域的中文分词工具
Home-page: http://github.com/rises-tech/ecws
Author: alxor
Author-email: alxor@live.cn
License: MIT
Keywords: ecws,3.0.5
Platform: any
Requires-Python: >=3.6
Requires-Dist: torch (==1.5.1)
Requires-Dist: allennlp (==1.0.0)
